excloud/__init__.py
excloud/client.py
excloud/exceptions.py
excloud/logging_config.py
excloud/sandbox.py
excloud-0.1.2.dist-info/licenses/LICENSE
excloud-0.1.2.dist-info/METADATA
excloud-0.1.2.dist-info/WHEEL
excloud-0.1.2.dist-info/top_level.txt
excloud-0.1.2.dist-info/RECORD
